concurrency_limiter/__init__.py
concurrency_limiter/py.typed
concurrency_limiter-1.1.0.dist-info/METADATA
concurrency_limiter-1.1.0.dist-info/WHEEL
concurrency_limiter-1.1.0.dist-info/licenses/LICENSE
concurrency_limiter-1.1.0.dist-info/RECORD
